datadog/__init__.py
datadog/api/__init__.py
datadog/api/api_client.py
datadog/api/comments.py
datadog/api/constants.py
datadog/api/downtimes.py
datadog/api/events.py
datadog/api/exceptions.py
datadog/api/graphs.py
datadog/api/hosts.py
datadog/api/http_client.py
datadog/api/infrastructure.py
datadog/api/metrics.py
datadog/api/monitors.py
datadog/api/resources.py
datadog/api/screenboards.py
datadog/api/service_checks.py
datadog/api/tags.py
datadog/api/timeboards.py
datadog/api/users.py
datadog/dogshell/__init__.py
datadog/dogshell/comment.py
datadog/dogshell/common.py
datadog/dogshell/downtime.py
datadog/dogshell/event.py
datadog/dogshell/host.py
datadog/dogshell/metric.py
datadog/dogshell/monitor.py
datadog/dogshell/screenboard.py
datadog/dogshell/search.py
datadog/dogshell/service_check.py
datadog/dogshell/tag.py
datadog/dogshell/timeboard.py
datadog/dogshell/wrap.py
datadog/dogstatsd/__init__.py
datadog/dogstatsd/base.py
datadog/dogstatsd/context.py
datadog/dogstatsd/context_async.py
datadog/dogstatsd/route.py
datadog/threadstats/__init__.py
datadog/threadstats/base.py
datadog/threadstats/constants.py
datadog/threadstats/events.py
datadog/threadstats/metrics.py
datadog/threadstats/periodic_timer.py
datadog/threadstats/reporters.py
datadog/util/__init__.py
datadog/util/compat.py
datadog/util/config.py
datadog/util/format.py
datadog/util/hostname.py
python26datadog-0.16.0.dist-info/DESCRIPTION.rst
python26datadog-0.16.0.dist-info/METADATA
python26datadog-0.16.0.dist-info/RECORD
python26datadog-0.16.0.dist-info/WHEEL
python26datadog-0.16.0.dist-info/entry_points.txt
python26datadog-0.16.0.dist-info/metadata.json
python26datadog-0.16.0.dist-info/top_level.txt
