Metadata-Version: 2.0
Name: python26datadog
Version: 0.16.0
Summary: The Datadog Python library
Home-page: http://www.datadoghq.com
Author: Datadog, Inc.
Author-email: dev@datadoghq.com
License: BSD
Keywords: datadog data
Platform: UNKNOWN
Classifier: License :: OSI Approved :: BSD License
Classifier: Operating System :: OS Independent
Classifier: Programming Language :: Python :: 2.6
Classifier: Programming Language :: Python :: 2.7
Classifier: Programming Language :: Python :: 3.3
Classifier: Programming Language :: Python :: 3.4
Classifier: Programming Language :: Python :: 3.5
Classifier: Programming Language :: Python :: Implementation :: PyPy
Requires-Dist: decorator (>=3.3.2)
Requires-Dist: requests (>=2.6.0)
Requires-Dist: simplejson (>=2.0.9)
